{
	"info": {
		"_postman_id": "41af5efb-da0e-4cf0-8667-b552f89ca0ee",
		"name": "Employee_Perks",
		"schema": "https://schema.getpostman.com/json/collection/v2.1.0/collection.json",
		"_exporter_id": "26462060"
	},
	"item": [
		{
			"name": "Employee Requests",
			"item": [
				{
					"name": "GET All Employees",
					"request": {
						"auth": {
							"type": "basic",
							"basic": [
								{
									"key": "username",
									"value": "mary",
									"type": "string"
								},
								{
									"key": "password",
									"value": "fun123",
									"type": "string"
								}
							]
						},
						"method": "GET",
						"header": [],
						"url": {
							"raw": "http://localhost:8080/api/employees",
							"protocol": "http",
							"host": [
								"localhost"
							],
							"port": "8080",
							"path": [
								"api",
								"employees"
							]
						}
					},
					"response": []
				},
				{
					"name": "GET Employee By Id",
					"request": {
						"auth": {
							"type": "basic",
							"basic": [
								{
									"key": "username",
									"value": "susan",
									"type": "string"
								},
								{
									"key": "password",
									"value": "test123",
									"type": "string"
								}
							]
						},
						"method": "GET",
						"header": [],
						"url": {
							"raw": "http://localhost:8080/api/employees/1",
							"protocol": "http",
							"host": [
								"localhost"
							],
							"port": "8080",
							"path": [
								"api",
								"employees",
								"1"
							]
						}
					},
					"response": []
				},
				{
					"name": "Create Employee",
					"request": {
						"method": "POST",
						"header": [],
						"body": {
							"mode": "raw",
							"raw": "{\r\n    \"firstName\" : \"Valli1\",\r\n    \"lastName\" :\"Muthu\",\r\n    \"email\" : \"valli@gmail.com\",\r\n    \"creditPoints\" : 400\r\n}",
							"options": {
								"raw": {
									"language": "json"
								}
							}
						},
						"url": {
							"raw": "http://localhost:8080/api/employees",
							"protocol": "http",
							"host": [
								"localhost"
							],
							"port": "8080",
							"path": [
								"api",
								"employees"
							]
						}
					},
					"response": []
				},
				{
					"name": "Update Employee",
					"request": {
						"method": "PUT",
						"header": [],
						"body": {
							"mode": "raw",
							"raw": "{\r\n    \"firstName\" : \"Valli\",\r\n    \"lastName\" :\"Muthu\",\r\n    \"email\" : \"valli1@gmail.com\"\r\n}",
							"options": {
								"raw": {
									"language": "json"
								}
							}
						},
						"url": {
							"raw": "http://localhost:8080/api/employees",
							"protocol": "http",
							"host": [
								"localhost"
							],
							"port": "8080",
							"path": [
								"api",
								"employees"
							]
						}
					},
					"response": []
				},
				{
					"name": "Delete Employee",
					"request": {
						"method": "DELETE",
						"header": [],
						"url": {
							"raw": "http://localhost:8080/api/employees/7",
							"protocol": "http",
							"host": [
								"localhost"
							],
							"port": "8080",
							"path": [
								"api",
								"employees",
								"7"
							]
						}
					},
					"response": []
				}
			]
		},
		{
			"name": "Product Requests",
			"item": [
				{
					"name": "GET All Products",
					"request": {
						"method": "GET",
						"header": [],
						"url": {
							"raw": "http://localhost:8080/api/products",
							"protocol": "http",
							"host": [
								"localhost"
							],
							"port": "8080",
							"path": [
								"api",
								"products"
							]
						}
					},
					"response": []
				},
				{
					"name": "Get Product By Id",
					"request": {
						"method": "GET",
						"header": [],
						"url": {
							"raw": "http://localhost:8080/api/products/2",
							"protocol": "http",
							"host": [
								"localhost"
							],
							"port": "8080",
							"path": [
								"api",
								"products",
								"2"
							]
						}
					},
					"response": []
				},
				{
					"name": "Create Product",
					"request": {
						"method": "POST",
						"header": [],
						"body": {
							"mode": "raw",
							"raw": "{\r\n    \"productName\" : \"AirPod\",\r\n    \"quantity\" : 10,\r\n    \"points\": 400\r\n}",
							"options": {
								"raw": {
									"language": "json"
								}
							}
						},
						"url": {
							"raw": "http://localhost:8080/api/products",
							"protocol": "http",
							"host": [
								"localhost"
							],
							"port": "8080",
							"path": [
								"api",
								"products"
							]
						}
					},
					"response": []
				},
				{
					"name": "Update Product",
					"request": {
						"method": "PUT",
						"header": [],
						"body": {
							"mode": "raw",
							"raw": "{\r\n    \"productName\" : \"AirPod\",\r\n    \"quantity\" : 20,\r\n    \"points\": 400\r\n}",
							"options": {
								"raw": {
									"language": "json"
								}
							}
						},
						"url": {
							"raw": "http://localhost:8080/api/products",
							"protocol": "http",
							"host": [
								"localhost"
							],
							"port": "8080",
							"path": [
								"api",
								"products"
							]
						}
					},
					"response": []
				},
				{
					"name": "Delete Product",
					"request": {
						"method": "DELETE",
						"header": [],
						"url": {
							"raw": "http://localhost:8080/api/products/6",
							"protocol": "http",
							"host": [
								"localhost"
							],
							"port": "8080",
							"path": [
								"api",
								"products",
								"6"
							]
						}
					},
					"response": []
				}
			]
		},
		{
			"name": "Order Requests",
			"item": [
				{
					"name": "Get All Orders",
					"request": {
						"method": "GET",
						"header": [],
						"url": {
							"raw": "http://localhost:8080/api/orders",
							"protocol": "http",
							"host": [
								"localhost"
							],
							"port": "8080",
							"path": [
								"api",
								"orders"
							]
						}
					},
					"response": []
				},
				{
					"name": "GET Order By Id",
					"protocolProfileBehavior": {
						"disableBodyPruning": true
					},
					"request": {
						"auth": {
							"type": "basic",
							"basic": [
								{
									"key": "username",
									"value": "susan",
									"type": "string"
								},
								{
									"key": "password",
									"value": "fun123",
									"type": "string"
								}
							]
						},
						"method": "GET",
						"header": [],
						"body": {
							"mode": "raw",
							"raw": "{\r\n    \"empId\": 5,\r\n    \"products\": [\r\n        {\r\n            \"productId\": 5,\r\n            \"quantity\": 1\r\n        },\r\n        {\r\n            \"productId\": 4,\r\n            \"quantity\": 1\r\n        }\r\n    ]\r\n}",
							"options": {
								"raw": {
									"language": "json"
								}
							}
						},
						"url": {
							"raw": "http://localhost:8080/api/orders/105",
							"protocol": "http",
							"host": [
								"localhost"
							],
							"port": "8080",
							"path": [
								"api",
								"orders",
								"105"
							]
						}
					},
					"response": []
				},
				{
					"name": "Create Order",
					"request": {
						"method": "POST",
						"header": [],
						"body": {
							"mode": "raw",
							"raw": "{\r\n    \"empId\" : 5,\r\n    \"products\":[\r\n        {\r\n        \"productId\" : 2,\r\n        \"quantity\" : 2\r\n        }\r\n\r\n    ]\r\n}",
							"options": {
								"raw": {
									"language": "json"
								}
							}
						},
						"url": {
							"raw": "http://localhost:8080/api/orders",
							"protocol": "http",
							"host": [
								"localhost"
							],
							"port": "8080",
							"path": [
								"api",
								"orders"
							]
						}
					},
					"response": []
				},
				{
					"name": "Delete Order",
					"request": {
						"method": "DELETE",
						"header": [],
						"url": {
							"raw": "http://localhost:8080/api/orders/121",
							"protocol": "http",
							"host": [
								"localhost"
							],
							"port": "8080",
							"path": [
								"api",
								"orders",
								"121"
							]
						}
					},
					"response": []
				}
			]
		}
	]
}